dbstats/__init__.py
dbstats/models.py
dbstats/sql.py
dbstats-0.2.2.data/scripts/get-transmart-stats.py
dbstats-0.2.2.dist-info/METADATA
dbstats-0.2.2.dist-info/WHEEL
dbstats-0.2.2.dist-info/top_level.txt
dbstats-0.2.2.dist-info/RECORD
