Metadata-Version: 2.1
Name: dbstats
Version: 0.2.2
Summary: dbstats
Home-page: https://github.com/jgeofil/dbstats
Author: Jeremy Georges-Filteau
Author-email: jeremy@thehyve.nl
License: MIT
Platform: UNKNOWN
Requires-Python: >=3.0
Requires-Dist: numpy
Requires-Dist: psycopg2
Requires-Dist: sparse
Requires-Dist: tqdm
